README.rst
setup.cfg
setup.py
./__init__.py
./box_type.xml
./carrier.py
./carrier.xml
./carrier_service.xml
./party.py
./sale.py
./sale.xml
./stock.py
./stock.xml
./tryton.cfg
./tests/conftest.py
./tests/test_shipping.py
./tests/test_view_depends.py
./view/carrier_form.xml
./view/sale_configuration_form.xml
./view/shipment_view_form.xml
fio_shipping_fedex.egg-info/PKG-INFO
fio_shipping_fedex.egg-info/SOURCES.txt
fio_shipping_fedex.egg-info/dependency_links.txt
fio_shipping_fedex.egg-info/entry_points.txt
fio_shipping_fedex.egg-info/not-zip-safe
fio_shipping_fedex.egg-info/requires.txt
fio_shipping_fedex.egg-info/top_level.txt